{"meta":{"id":"6C8BBEFF-93F4-495B-A8CB-7F9BAA5D0F79","version":"0.7","description":"Tubescreamer, Fireball, EQ, Reverb","icon":"icon.png","name":"Engl Fireball"},"sigpath":[{"active":true,"type":"speaker_fx","dspId":"bias.noisegate","params":[{"index":0,"value":0.54553598165512085},{"index":1,"value":0.56945902109146118}]},{"active":false,"type":"speaker_fx","dspId":"LA2AComp","params":[{"value":0,"index":0},{"value":0.71264445781707764,"index":1},{"index":2,"value":0.72480618953704834}]},{"active":true,"type":"speaker_fx","dspId":"DistortionTS9","params":[{"index":0,"value":0.12645499408245087},{"index":1,"value":0.81613898277282715},{"value":1,"index":2}]},{"active":true,"type":"speaker_fx","dspId":"SwitchAxeLead","params":[{"value":0.69999998807907104,"index":0},{"index":1,"value":0.50397598743438721},{"index":2,"value":0.056295000016689301},{"index":3,"value":1},{"index":4,"value":0.69999998807907104}]},{"active":false,"type":"speaker_fx","dspId":"Tremolo","params":[{"value":0.45413351058959961,"index":0},{"value":0.69993364810943604,"index":1},{"index":2,"value":0.5961538553237915}]},{"active":false,"type":"speaker_fx","dspId":"DelayMono","params":[{"value":0.38177722692489624,"index":0},{"index":1,"value":0.39830508828163147},{"index":2,"value":0.73633134365081787},{"index":3,"value":0.60000002384185791},{"value":0,"index":4}]},{"active":true,"type":"speaker_fx","dspId":"bias.reverb","params":[{"value":0.28571429848670959,"index":0},{"index":1,"value":0.40835356712341309},{"index":2,"value":0.28948888182640076},{"value":0.38831719756126404,"index":3},{"value":0.58214282989501953,"index":4},{"value":0.65000003576278687,"index":5},{"index":6,"value":0.20000000298023224}]}],"type":"jamup_speaker","bpm":120}